{
    "14/06": {
        "06:00": {
            "Llegada al aeropuerto": 0
        },
        "07:00": {
            "Desayuno en el aeropuerto": 0
        },
        "08:00": {
            "Bus a Sydney": 0
        },
        "09:30": {
            "Bus al tour": 0
        },
        "10:00": {
            "Tour 1 20 AUD": 0,
            "Tour 2 25 AUD": 2
        },
        "12:00": {
            "Bus a otra actividad": 0
        },
        "12:30": {
            "Actividad 1": 0,
            "Actividad 2": 0
        },
        "18:00": {
            "Cena": 0
        }
    },
    "15/06": {
        "08:00": {
            "Desayuno en el hotel": 0
        },
        "09:00": {
            "Visita al parque": 0
        },
        "12:00": {
            "Almuerzo en el restaurante": 0
        },
        "15:00": {
            "Visita al museo": 0
        },
        "18:00": {
            "Cena en el centro": 0
        }
    }
}